LbCondaWrappers/__init__.py
LbCondaWrappers-0.5.2.dist-info/LICENSE
LbCondaWrappers-0.5.2.dist-info/METADATA
LbCondaWrappers-0.5.2.dist-info/WHEEL
LbCondaWrappers-0.5.2.dist-info/entry_points.txt
LbCondaWrappers-0.5.2.dist-info/top_level.txt
LbCondaWrappers-0.5.2.dist-info/RECORD
