Metadata-Version: 2.1
Name: LbCondaWrappers
Version: 0.5.2
Summary: Wrappers for using LHCb CVMFS conda installations
Author: LHCb
Project-URL: Homepage, https://gitlab.cern.ch/lhcb-core/LbCondaWrappers
Project-URL: Bug Reports, https://gitlab.cern.ch/lhcb-core/LbCondaWrappers/issues
Project-URL: Source, https://gitlab.cern.ch/lhcb-core/LbCondaWrappers
Keywords: LHCb,Core,task,runner
Classifier: Development Status :: 4 - Beta
Classifier: License :: OSI Approved :: GNU General Public License v3 or later (GPLv3+)
Classifier: Programming Language :: Python :: 3
Requires-Python: >=3.9
License-File: LICENSE
Requires-Dist: lb_telemetry>=0.5.0
Provides-Extra: testing
Requires-Dist: pytest; extra == "testing"
Requires-Dist: pytest-cov; extra == "testing"
